{
  "android-instant": {
    "REMOTE_SERVER_ROOT": "",
    "host": "",
    "pathPattern": "",
    "recordPath": "",
    "scheme": "https",
    "skipRecord": false
  },
  "appBundle": false,
  "baidugame": {
    "REMOTE_SERVER_ROOT": "",
    "appid": "testappid",
    "orientation": "portrait",
    "subContext": ""
  },
  "encryptJs": true,
  "excludeScenes": [],
  "fb-instant-games": {},
  "includeSDKBox": false,
  "inlineSpriteFrames": true,
  "inlineSpriteFrames_native": true,
  "md5Cache": true,
  "mergeStartScene": false,
  "optimizeHotUpdate": false,
  "orientation": {
    "landscapeLeft": true,
    "landscapeRight": true,
    "portrait": false,
    "upsideDown": false
  },
  "packageName": "org.cocos2d.FENDI",
  "qqplay": {
    "REMOTE_SERVER_ROOT": "",
    "orientation": "portrait",
    "zip": false
  },
  "startScene": "f3c45e4b-f5d2-4e2d-8b0b-618132e829c6",
  "title": "FENDI",
  "webOrientation": "landscape",
  "wechatgame": {
    "REMOTE_SERVER_ROOT": "https://cdn.duligame.cn/minigame-fendi/WeChatTest_2",
    "appid": "wx4b0dc8d75a0857b7",
    "orientation": "landscapeRight",
    "separate_engine": false,
    "subContext": "wx-open-data-project"
  },
  "xxteaKey": "80f9fc4f-3eae-4c",
  "zipCompressJs": true
}